{
  "project_info": {
    "project_number": "539172038520",
    "firebase_url": "https://pushnotification-c49c8.firebaseio.com",
    "project_id": "pushnotification-c49c8",
    "storage_bucket": "pushnotification-c49c8.appspot.com"
  },
  "client": [
    {
      "client_info": {
        "mobilesdk_app_id": "1:539172038520:android:bb32f86a6378d6d0",
        "android_client_info": {
          "package_name": "com.suzit.firebase"
        }
      },
      "oauth_client": [
        {
          "client_id": "539172038520-grs8g4tsqd31f4rhe0cs3g2o5eu65p8v.apps.googleusercontent.com",
          "client_type": 3
        }
      ],
      "api_key": [
        {
          "current_key": "AIzaSyAzJ9O-xopK7nT6pCpEMvFr9lwp9UKEpGk"
        }
      ],
      "services": {
        "analytics_service": {
          "status": 1
        },
        "appinvite_service": {
          "status": 1,
          "other_platform_oauth_client": []
        },
        "ads_service": {
          "status": 2
        }
      }
    }
  ],
  "configuration_version": "1"
}